[
    {
      "id": 1,
      "title": "Modern Apartment in Downtown",
      "address": "123 Main St, New York, NY 10001",
      "description": "A stylish 2-bedroom apartment with a great city view.",
      "price": 2500,
      "type": "Rent",
      "bedrooms": 2,
      "bathrooms": 1,
      "image": "./images/h1.jpg"
    },
    {
      "id": 2,
      "title": "Luxury Villa with Pool",
      "address": "789 Sunset Blvd, Beverly Hills, CA 90210",
      "description": "A stunning 5-bedroom villa with a private pool and garden.",
      "price": 3500000,
      "type": "Sale",
      "bedrooms": 5,
      "bathrooms": 4,
      "image": "./images/h2.jpg"
    },
    {
      "id": 3,
      "title": "Cozy Family House",
      "address": "456 Oak St, Austin, TX 73301",
      "description": "A perfect 3-bedroom home for families, near schools and parks.",
      "price": 1800,
      "type": "Rent",
      "bedrooms": 3,
      "bathrooms": 2,
      "image": "./images/h3.jpg"
    },
    {
      "id": 4,
      "title": "Modern Condo with Ocean View",
      "address": "12 Beach Rd, Miami, FL 33139",
      "description": "A high-end condo with breathtaking ocean views and amenities.",
      "price": 500000,
      "type": "Sale",
      "bedrooms": 2,
      "bathrooms": 2,
      "image": "./images/h4.jpg"
    },
    {
      "id": 5,
      "title": "Affordable Studio Apartment",
      "address": "88 City Lane, Chicago, IL 60601",
      "description": "A cozy studio apartment in a prime location, ideal for singles.",
      "price": 1200,
      "type": "Rent",
      "bedrooms": 1,
      "bathrooms": 1,
      "image": "./images/h5.jpg"
    },
    {
      "id": 6,
      "title": "Spacious Townhouse",
      "address": "155 Maple Ave, Denver, CO 80203",
      "description": "A beautiful 4-bedroom townhouse with a large backyard.",
      "price": 450000,
      "type": "Sale",
      "bedrooms": 4,
      "bathrooms": 3,
      "image": "./images/h6.jpg"
    },
    {
      "id": 7,
      "title": "Luxury Penthouse Suite",
      "address": "222 Skyline Tower, Los Angeles, CA 90015",
      "description": "A top-floor penthouse with a private rooftop and skyline views.",
      "price": 6000,
      "type": "Rent",
      "bedrooms": 3,
      "bathrooms": 3,
      "image": "./images/h7.jpg"
    },
    {
      "id": 8,
      "title": "Suburban Family Home",
      "address": "42 Greenway, Houston, TX 77005",
      "description": "A charming family home with a spacious front yard.",
      "price": 320000,
      "type": "Sale",
      "bedrooms": 3,
      "bathrooms": 2,
      "image": "./images/h8.jpg"
    },
    {
      "id": 9,
      "title": "Urban Loft in City Center",
      "address": "5 Downtown St, Seattle, WA 98101",
      "description": "A stylish loft with high ceilings and industrial decor.",
      "price": 2800,
      "type": "Rent",
      "bedrooms": 2,
      "bathrooms": 2,
      "image": "./images/h9.jpg"
    },
    {
      "id": 10,
      "title": "Luxury Mansion with Tennis Court",
      "address": "900 Elite Drive, Palm Beach, FL 33480",
      "description": "A grand estate with private amenities including a tennis court.",
      "price": 9500000,
      "type": "Sale",
      "bedrooms": 7,
      "bathrooms": 6,
      "image": "./images/h10.jpg"
    },
    {
        "id": 1,
        "title": "Luxury Apartment",
        "address": "123 Main Street, New York, NY",
        "description": "A modern 3-bedroom apartment in the heart of the city.",
        "price": 250000,
        "type": "Sale",
        "bedrooms": 3,
        "bathrooms": 2,
        "image": "./images/h11.jpg"
    },
    {
        "id": 2,
        "title": "Cozy House",
        "address": "456 Elm Street, Los Angeles, CA",
        "description": "A cozy 2-bedroom home with a spacious backyard.",
        "price": 1500,
        "type": "Rent",
        "bedrooms": 2,
        "bathrooms": 1,
        "image": "./images/h12.jpg"
    },
    {
        "id": 3,
        "title": "Modern Condo",
        "address": "789 Oak Avenue, Chicago, IL",
        "description": "A stylish condo with modern amenities.",
        "price": 300000,
        "type": "Sale",
        "bedrooms": 2,
        "bathrooms": 2,
        "image": "./images/h13.jpg"
    },
    {
        "id": 4,
        "title": "Spacious Family Home",
        "address": "101 Pine Street, Houston, TX",
        "description": "A spacious family home with a large garden.",
        "price": 400000,
        "type": "Sale",
        "bedrooms": 4,
        "bathrooms": 3,
        "image": "./images/h14.jpg"
    },
    {
        "id": 5,
        "title": "Beachfront Property",
        "address": "202 Maple Avenue, San Diego, CA",
        "description": "A beachfront property with ocean views.",
        "price": 1200,
        "type": "Rent",
        "bedrooms": 3,
        "bathrooms": 2,
        "image": "./images/h15.jpg"
    },
    {
        "id": 6,
        "title": "Rustic Cabin",
        "address": "303 Cedar Lane, Phoenix, AZ",
        "description": "A rustic cabin surrounded by nature.",
        "price": 180000,
        "type": "Sale",
        "bedrooms": 2,
        "bathrooms": 1,
        "image": "./images/h16.jpg"
    },
    {
        "id": 7,
        "title": "Contemporary Townhouse",
        "address": "404 Birch Street, Philadelphia, PA",
        "description": "A contemporary townhouse with open floor plans.",
        "price": 350000,
        "type": "Sale",
        "bedrooms": 3,
        "bathrooms": 2,
        "image": "./images/h17.jpg"
    },
    {
        "id": 8,
        "title": "Sleek Penthouse",
        "address": "505 Willow Road, San Antonio, TX",
        "description": "A sleek penthouse with panoramic city views.",
        "price": 500000,
        "type": "Sale",
        "bedrooms": 4,
        "bathrooms": 3,
        "image": "./images/h18.jpg"
    },
    {
        "id": 9,
        "title": "Charming House",
        "address": "606 Cherry Lane, Dallas, TX",
        "description": "A charming house in a quiet neighborhood.",
        "price": 280000,
        "type": "Sale",
        "bedrooms": 3,
        "bathrooms": 2,
        "image": "./images/h19.jpg"
    },
    {
        "id": 10,
        "title": "Luxury Villa",
        "address": "707 Walnut Street, San Jose, CA",
        "description": "A luxurious villa with stunning views.",
        "price": 800000,
        "type": "Sale",
        "bedrooms": 5,
        "bathrooms": 4,
        "image": "./images/h20.jpg"
    },
    {
        "id": 11,
        "title": "Urban Loft",
        "address": "808 Main Street, New York, NY",
        "description": "An urban loft with industrial-style design.",
        "price": 2200,
        "type": "Rent",
        "bedrooms": 1,
        "bathrooms": 1,
        "image": "./images/h21.jpg"
    },
    {
        "id": 12,
        "title": "Suburban Home",
        "address": "909 Elm Street, Los Angeles, CA",
        "description": "A suburban home with a large backyard.",
        "price": 320000,
        "type": "Sale",
        "bedrooms": 3,
        "bathrooms": 2,
        "image": "./images/h22.jpg"
    },
    {
        "id": 13,
        "title": "Lakeside Cottage",
        "address": "1010 Oak Avenue, Chicago, IL",
        "description": "A cozy lakeside cottage with beautiful views.",
        "price": 270000,
        "type": "Sale",
        "bedrooms": 2,
        "bathrooms": 1,
        "image": "./images/h23.jpg"
    },
    {
        "id": 14,
        "title": "Downtown Apartment",
        "address": "1111 Pine Street, Houston, TX",
        "description": "A modern apartment in the downtown area.",
        "price": 1800,
        "type": "Rent",
        "bedrooms": 2,
        "bathrooms": 2,
        "image": "./images/h24.jpg"
    },
    {
        "id": 15,
        "title": "Mountain Retreat",
        "address": "1212 Maple Avenue, San Diego, CA",
        "description": "A peaceful mountain retreat.",
        "price": 310000,
        "type": "Sale",
        "bedrooms": 3,
        "bathrooms": 2,
        "image": "./images/h25.jpg"
    },
    {
        "id": 16,
        "title": "City Studio",
        "address": "1313 Cedar Lane, Phoenix, AZ",
        "description": "A compact studio in the city center.",
        "price": 900,
        "type": "Rent",
        "bedrooms": 1,
        "bathrooms": 1,
        "image": "./images/h26.jpg"
    },
    {
        "id": 17,
        "title": "Historic Townhouse",
        "address": "1414 Birch Street, Philadelphia, PA",
        "description": "A historic townhouse with classic charm.",
        "price": 450000,
        "type": "Sale",
        "bedrooms": 4,
        "bathrooms": 3,
        "image": "./images/h27.jpg"
    },
    {
        "id": 18,
        "title": "Modern Duplex",
        "address": "1515 Willow Road, San Antonio, TX",
        "description": "A modern duplex with sleek interiors.",
        "price": 380000,
        "type": "Sale",
        "bedrooms": 3,
        "bathrooms": 2,
        "image": "./images/h28.jpg"
    },
    {
        "id": 19,
        "title": "Country Home",
        "address": "1616 Cherry Lane, Dallas, TX",
        "description": "A spacious country home with a large garden.",
        "price": 290000,
        "type": "Sale",
        "bedrooms": 4,
        "bathrooms": 3,
        "image": "./images/h29.jpg"
    },
    {
        "id": 20,
        "title": "Beach House",
        "address": "1717 Walnut Street, San Jose, CA",
        "description": "A beautiful beach house with ocean views.",
        "price": 950000,
        "type": "Sale",
        "bedrooms": 5,
        "bathrooms": 4,
        "image": "./images/h30.jpg"
    }
]  